config_autogenerate_utils/__init__.py
config_autogenerate_utils/utils.py
cap_pipeline_config_utils-0.0.1.dist-info/LICENSE
cap_pipeline_config_utils-0.0.1.dist-info/METADATA
cap_pipeline_config_utils-0.0.1.dist-info/WHEEL
cap_pipeline_config_utils-0.0.1.dist-info/top_level.txt
cap_pipeline_config_utils-0.0.1.dist-info/RECORD
